artefacts_toolkit_rosbag/__init__.py
artefacts_toolkit_rosbag/image_topics.py
artefacts_toolkit_rosbag/message_topics.py
artefacts_toolkit_rosbag/rosbag.py
artefacts_toolkit_rosbag/version.py
artefacts_toolkit_rosbag-0.4.0.dist-info/METADATA
artefacts_toolkit_rosbag-0.4.0.dist-info/WHEEL
artefacts_toolkit_rosbag-0.4.0.dist-info/top_level.txt
artefacts_toolkit_rosbag-0.4.0.dist-info/RECORD
